qiskit/providers/ibmq/VERSION.txt
qiskit/providers/ibmq/__init__.py
qiskit/providers/ibmq/accountprovider.py
qiskit/providers/ibmq/apiconstants.py
qiskit/providers/ibmq/backendjoblimit.py
qiskit/providers/ibmq/backendreservation.py
qiskit/providers/ibmq/exceptions.py
qiskit/providers/ibmq/ibmqbackend.py
qiskit/providers/ibmq/ibmqbackendservice.py
qiskit/providers/ibmq/ibmqfactory.py
qiskit/providers/ibmq/runner_result.py
qiskit/providers/ibmq/version.py
qiskit/providers/ibmq/api/__init__.py
qiskit/providers/ibmq/api/exceptions.py
qiskit/providers/ibmq/api/session.py
qiskit/providers/ibmq/api/clients/__init__.py
qiskit/providers/ibmq/api/clients/account.py
qiskit/providers/ibmq/api/clients/auth.py
qiskit/providers/ibmq/api/clients/base.py
qiskit/providers/ibmq/api/clients/experiment.py
qiskit/providers/ibmq/api/clients/runtime.py
qiskit/providers/ibmq/api/clients/runtime_ws.py
qiskit/providers/ibmq/api/clients/utils.py
qiskit/providers/ibmq/api/clients/version.py
qiskit/providers/ibmq/api/clients/websocket.py
qiskit/providers/ibmq/api/rest/__init__.py
qiskit/providers/ibmq/api/rest/account.py
qiskit/providers/ibmq/api/rest/analysis_result.py
qiskit/providers/ibmq/api/rest/backend.py
qiskit/providers/ibmq/api/rest/base.py
qiskit/providers/ibmq/api/rest/experiment.py
qiskit/providers/ibmq/api/rest/job.py
qiskit/providers/ibmq/api/rest/root.py
qiskit/providers/ibmq/api/rest/runtime.py
qiskit/providers/ibmq/api/rest/utils/__init__.py
qiskit/providers/ibmq/api/rest/utils/data_mapper.py
qiskit/providers/ibmq/credentials/__init__.py
qiskit/providers/ibmq/credentials/configrc.py
qiskit/providers/ibmq/credentials/credentials.py
qiskit/providers/ibmq/credentials/environ.py
qiskit/providers/ibmq/credentials/exceptions.py
qiskit/providers/ibmq/credentials/hubgroupproject.py
qiskit/providers/ibmq/credentials/updater.py
qiskit/providers/ibmq/experiment/__init__.py
qiskit/providers/ibmq/experiment/constants.py
qiskit/providers/ibmq/experiment/device_component.py
qiskit_ibmq_provider-0.20.2.dist-info/LICENSE.txt
qiskit_ibmq_provider-0.20.2.dist-info/METADATA
qiskit_ibmq_provider-0.20.2.dist-info/WHEEL
qiskit_ibmq_provider-0.20.2.dist-info/top_level.txt
qiskit_ibmq_provider-0.20.2.dist-info/RECORD
