Metadata-Version: 2.1
Name: qiskit-ibmq-provider
Version: 0.20.2
Summary: Qiskit provider for accessing the quantum devices and simulators at IBMQ
Home-page: https://github.com/Qiskit/qiskit-ibmq-provider
Author: Qiskit Development Team
Author-email: hello@qiskit.org
License: Apache 2.0
Project-URL: Bug Tracker, https://github.com/Qiskit/qiskit-ibmq-provider/issues
Project-URL: Documentation, https://qiskit.org/documentation/
Project-URL: Source Code, https://github.com/Qiskit/qiskit-ibmq-provider
Keywords: qiskit sdk quantum api ibmq
Classifier: Environment :: Console
Classifier: License :: OSI Approved :: Apache Software License
Classifier: Intended Audience :: Developers
Classifier: Intended Audience :: Science/Research
Classifier: Operating System :: Microsoft :: Windows
Classifier: Operating System :: MacOS
Classifier: Operating System :: POSIX :: Linux
Classifier: Programming Language :: Python :: 3 :: Only
Classifier: Programming Language :: Python :: 3.6
Classifier: Programming Language :: Python :: 3.7
Classifier: Programming Language :: Python :: 3.8
Classifier: Programming Language :: Python :: 3.9
Classifier: Topic :: Scientific/Engineering
Requires-Python: >=3.7
Provides-Extra: visualization
License-File: LICENSE.txt
